[
  {
    "inputs": [
      {
        "internalType": "contract IPookyball",
        "name": "_pookyball",
        "type": "address"
      },
      {
        "internalType": "contract IWaitList",
        "name": "_waitlist",
        "type": "address"
      },
      {
        "internalType": "address",
        "name": "_treasury",
        "type": "address"
      },
      {
        "components": [
          {
            "internalType": "enum PookyballRarity",
            "name": "rarity",
            "type": "uint8"
          },
          {
            "internalType": "uint256",
            "name": "luxury",
            "type": "uint256"
          },
          {
            "internalType": "uint256",
            "name": "supply",
            "type": "uint256"
          },
          {
            "internalType": "uint256",
            "name": "minted",
            "type": "uint256"
          },
          {
            "internalType": "uint256",
            "name": "price",
            "type": "uint256"
          }
        ],
        "internalType": "struct Template[]",
        "name": "_templates",
        "type": "tuple[]"
      }
    ],
    "stateMutability": "nonpayable",
    "type": "constructor"
  },
  {
    "inputs": [
      {
        "internalType": "address",
        "name": "account",
        "type": "address"
      }
    ],
    "name": "Ineligible",
    "type": "error"
  },
  {
    "inputs": [
      {
        "internalType": "uint256",
        "name": "templateId",
        "type": "uint256"
      },
      {
        "internalType": "uint256",
        "name": "remaining",
        "type": "uint256"
      }
    ],
    "name": "InsufficientSupply",
    "type": "error"
  },
  {
    "inputs": [
      {
        "internalType": "uint256",
        "name": "expected",
        "type": "uint256"
      },
      {
        "internalType": "uint256",
        "name": "actual",
        "type": "uint256"
      }
    ],
    "name": "InsufficientValue",
    "type": "error"
  },
  {
    "inputs": [
      {
        "internalType": "address",
        "name": "recipient",
        "type": "address"
      },
      {
        "internalType": "uint256",
        "name": "amount",
        "type": "uint256"
      }
    ],
    "name": "TransferFailed",
    "type": "error"
  },
  {
    "anonymous": false,
    "inputs": [
      {
        "indexed": true,
        "internalType": "address",
        "name": "account",
        "type": "address"
      },
      {
        "indexed": true,
        "internalType": "uint256",
        "name": "templateId",
        "type": "uint256"
      },
      {
        "indexed": false,
        "internalType": "uint256",
        "name": "quantity",
        "type": "uint256"
      },
      {
        "indexed": false,
        "internalType": "uint256",
        "name": "value",
        "type": "uint256"
      }
    ],
    "name": "Sale",
    "type": "event"
  },
  {
    "inputs": [
      {
        "internalType": "uint256",
        "name": "templateId",
        "type": "uint256"
      },
      {
        "internalType": "address",
        "name": "recipient",
        "type": "address"
      },
      {
        "internalType": "uint256",
        "name": "quantity",
        "type": "uint256"
      }
    ],
    "name": "ineligibilityReason",
    "outputs": [
      {
        "internalType": "string",
        "name": "",
        "type": "string"
      }
    ],
    "stateMutability": "view",
    "type": "function"
  },
  {
    "inputs": [],
    "name": "lastTemplateId",
    "outputs": [
      {
        "internalType": "uint256",
        "name": "",
        "type": "uint256"
      }
    ],
    "stateMutability": "view",
    "type": "function"
  },
  {
    "inputs": [
      {
        "internalType": "uint256",
        "name": "templateId",
        "type": "uint256"
      },
      {
        "internalType": "address",
        "name": "recipient",
        "type": "address"
      },
      {
        "internalType": "uint256",
        "name": "quantity",
        "type": "uint256"
      }
    ],
    "name": "mint",
    "outputs": [],
    "stateMutability": "payable",
    "type": "function"
  },
  {
    "inputs": [],
    "name": "pookyball",
    "outputs": [
      {
        "internalType": "contract IPookyball",
        "name": "",
        "type": "address"
      }
    ],
    "stateMutability": "view",
    "type": "function"
  },
  {
    "inputs": [
      {
        "internalType": "uint256",
        "name": "",
        "type": "uint256"
      }
    ],
    "name": "templates",
    "outputs": [
      {
        "internalType": "enum PookyballRarity",
        "name": "rarity",
        "type": "uint8"
      },
      {
        "internalType": "uint256",
        "name": "luxury",
        "type": "uint256"
      },
      {
        "internalType": "uint256",
        "name": "supply",
        "type": "uint256"
      },
      {
        "internalType": "uint256",
        "name": "minted",
        "type": "uint256"
      },
      {
        "internalType": "uint256",
        "name": "price",
        "type": "uint256"
      }
    ],
    "stateMutability": "view",
    "type": "function"
  },
  {
    "inputs": [],
    "name": "waitlist",
    "outputs": [
      {
        "internalType": "contract IWaitList",
        "name": "",
        "type": "address"
      }
    ],
    "stateMutability": "view",
    "type": "function"
  }
]
